{"status":{"3d3a7efaaecf678c97aa83930ed7388e":{"host":"example-host-a0","service":"Example service","status_information":null,"status":"DOWN","priority":0,"duration":"1m","duration_seconds":60,"md5id":"3d3a7efaaecf678c97aa83930ed7388e","index":1,"type":"host","alert_active":false,"is_flapping":false,"is_soft":true},"070001c646d1ab8354c86d721f14a7d9":{"host":"example-host-a4","service":"Example service","status_information":null,"status":"DOWN","priority":0,"duration":"1m","duration_seconds":60,"md5id":"070001c646d1ab8354c86d721f14a7d9","index":2,"type":"host","alert_active":false,"is_flapping":false,"is_soft":true},"376aee5c99ca934e3289121315ad7f6a":{"host":"example-host-a3","service":"Example service","status_information":null,"status":"DOWN","priority":0,"duration":"1m","duration_seconds":60,"md5id":"376aee5c99ca934e3289121315ad7f6a","index":3,"type":"host","alert_active":false,"is_flapping":false,"is_soft":true},"f314ad75562fa98b390731152298e3c2":{"host":"example-host-a2","service":"Example service","status_information":null,"status":"DOWN","priority":0,"duration":"1m","duration_seconds":60,"md5id":"f314ad75562fa98b390731152298e3c2","index":4,"type":"host","alert_active":false,"is_flapping":false,"is_soft":true},"ca8eba7732cec746be763f8647685d9f":{"host":"example-host-a1","service":"Example service","status_information":null,"status":"DOWN","priority":0,"duration":"1m","duration_seconds":60,"md5id":"ca8eba7732cec746be763f8647685d9f","index":5,"type":"host","alert_active":false,"is_flapping":false,"is_soft":true},"ca8a988c78b9b57ae70ef8b0fc2d9ee6":{"host":"example-host-b9","service":"Example service","status_information":null,"status":"CRITICAL","priority":0,"duration":"1m","duration_seconds":60,"md5id":"ca8a988c78b9b57ae70ef8b0fc2d9ee6","index":6,"type":"service","alert_active":false,"is_flapping":false,"is_soft":true},"fa2cd11cc0e67a3a37fb56985f279e75":{"host":"example-host-b8","service":"Example service","status_information":null,"status":"CRITICAL","priority":0,"duration":"1m","duration_seconds":60,"md5id":"fa2cd11cc0e67a3a37fb56985f279e75","index":7,"type":"service","alert_active":false,"is_flapping":false,"is_soft":true},"2babc81e5b070b1fdaacc6e6a5fd229c":{"host":"example-host-b10","service":"Example service","status_information":null,"status":"CRITICAL","priority":0,"duration":"1m","duration_seconds":60,"md5id":"2babc81e5b070b1fdaacc6e6a5fd229c","index":8,"type":"service","alert_active":false,"is_flapping":false,"is_soft":true},"65520d1ec7526d5cfa4482821653f3c5":{"host":"example-host-b14","service":"Example service","status_information":null,"status":"CRITICAL","priority":0,"duration":"1m","duration_seconds":60,"md5id":"65520d1ec7526d5cfa4482821653f3c5","index":9,"type":"service","alert_active":false,"is_flapping":false,"is_soft":true},"2309293f79bc07f99ab8af11032d5d3e":{"host":"example-host-b13","service":"Example service","status_information":null,"status":"CRITICAL","priority":0,"duration":"1m","duration_seconds":60,"md5id":"2309293f79bc07f99ab8af11032d5d3e","index":10,"type":"service","alert_active":false,"is_flapping":false,"is_soft":true},"94ce30dd0116f93999216ec460308273":{"host":"example-host-b12","service":"Example service","status_information":null,"status":"CRITICAL","priority":0,"duration":"1m","duration_seconds":60,"md5id":"94ce30dd0116f93999216ec460308273","index":11,"type":"service","alert_active":false,"is_flapping":false,"is_soft":true},"c245138dd9d446f017c035215f510520":{"host":"example-host-b11","service":"Example service","status_information":null,"status":"CRITICAL","priority":0,"duration":"1m","duration_seconds":60,"md5id":"c245138dd9d446f017c035215f510520","index":12,"type":"service","alert_active":false,"is_flapping":false,"is_soft":true},"c1275de6e677ac90b2b1682154125500":{"host":"example-host-b7","service":"Example service","status_information":null,"status":"CRITICAL","priority":0,"duration":"1m","duration_seconds":60,"md5id":"c1275de6e677ac90b2b1682154125500","index":13,"type":"service","alert_active":false,"is_flapping":false,"is_soft":true},"7937795f8a0f17f9e5fd946727616d49":{"host":"example-host-b6","service":"Example service","status_information":null,"status":"CRITICAL","priority":0,"duration":"1m","duration_seconds":60,"md5id":"7937795f8a0f17f9e5fd946727616d49","index":14,"type":"service","alert_active":false,"is_flapping":false,"is_soft":true},"798f664983455665bf404675bf773705":{"host":"example-host-b0","service":"Example service","status_information":null,"status":"CRITICAL","priority":0,"duration":"1m","duration_seconds":60,"md5id":"798f664983455665bf404675bf773705","index":15,"type":"service","alert_active":false,"is_flapping":false,"is_soft":true},"01b6740b159ead5d1be2d4d990065d45":{"host":"example-host-b2","service":"Example service","status_information":null,"status":"CRITICAL","priority":0,"duration":"1m","duration_seconds":60,"md5id":"01b6740b159ead5d1be2d4d990065d45","index":16,"type":"service","alert_active":false,"is_flapping":false,"is_soft":true},"8f92d46b282d2be5869c28bb8b6e18bd":{"host":"example-host-b1","service":"Example service","status_information":null,"status":"CRITICAL","priority":0,"duration":"1m","duration_seconds":60,"md5id":"8f92d46b282d2be5869c28bb8b6e18bd","index":17,"type":"service","alert_active":false,"is_flapping":false,"is_soft":true},"25459a15f7b1233cc6083cfd105da7e0":{"host":"example-host-b3","service":"Example service","status_information":null,"status":"CRITICAL","priority":0,"duration":"1m","duration_seconds":60,"md5id":"25459a15f7b1233cc6083cfd105da7e0","index":18,"type":"service","alert_active":false,"is_flapping":false,"is_soft":true},"5dab234aed32f6a06177169561df32e0":{"host":"example-host-b5","service":"Example service","status_information":null,"status":"CRITICAL","priority":0,"duration":"1m","duration_seconds":60,"md5id":"5dab234aed32f6a06177169561df32e0","index":19,"type":"service","alert_active":false,"is_flapping":false,"is_soft":true},"1827c3a2c700e3acd8442bd40f9139fa":{"host":"example-host-b4","service":"Example service","status_information":null,"status":"CRITICAL","priority":0,"duration":"1m","duration_seconds":60,"md5id":"1827c3a2c700e3acd8442bd40f9139fa","index":20,"type":"service","alert_active":false,"is_flapping":false,"is_soft":true},"66b91b4f040cbf3d4ae148b8f3be6f2c":{"host":"example-host-b2","service":"Example service2","status_information":null,"status":"WARNING","priority":0,"duration":"1m","duration_seconds":60,"md5id":"66b91b4f040cbf3d4ae148b8f3be6f2c","index":21,"type":"service","alert_active":false,"is_flapping":false,"is_soft":true},"53c6676154896395948627c9562484c1":{"host":"example-host-b0","service":"Example service2","status_information":null,"status":"WARNING","priority":0,"duration":"1m","duration_seconds":60,"md5id":"53c6676154896395948627c9562484c1","index":22,"type":"service","alert_active":false,"is_flapping":false,"is_soft":true},"d4e39709f3256af08cee639caa7c96a3":{"host":"example-host-b1","service":"Example service2","status_information":null,"status":"WARNING","priority":0,"duration":"1m","duration_seconds":60,"md5id":"d4e39709f3256af08cee639caa7c96a3","index":23,"type":"service","alert_active":false,"is_flapping":false,"is_soft":true},"3a445695f7b5fb12d47d8140dd0a861b":{"host":"example-host-c7","service":"Example service3","status_information":null,"status":"WARNING","priority":0,"duration":"1m","duration_seconds":60,"md5id":"3a445695f7b5fb12d47d8140dd0a861b","index":24,"type":"service","alert_active":false,"is_flapping":false,"is_soft":true},"9751321b845236f67c64ac7c3a51de27":{"host":"example-host-c6","service":"Example service3","status_information":null,"status":"WARNING","priority":0,"duration":"1m","duration_seconds":60,"md5id":"9751321b845236f67c64ac7c3a51de27","index":25,"type":"service","alert_active":false,"is_flapping":false,"is_soft":true}},"metadata":{"status_data_age":1,"status_update_interval":1,"reading_status_data_ok":1}}
